yami/__init__.py
yami/control.py
yami/cover_art.py
yami/main.py
yami/music.py
yami/playlist.py
yami/progress.py
yami/topbar.py
yami/util.py
yami/data/cover.ico
yami/data/folder.png
yami/data/icon.png
yami/data/image.png
yami/data/music.png
yami/data/oldpic.png
yami/data/pause.png
yami/data/play_arrow.png
yami/data/skip_next.png
yami/data/skip_prev.png
yami/data/theme.json
yami_music_player-1.0.1.dist-info/LICENSE
yami_music_player-1.0.1.dist-info/METADATA
yami_music_player-1.0.1.dist-info/WHEEL
yami_music_player-1.0.1.dist-info/entry_points.txt
yami_music_player-1.0.1.dist-info/top_level.txt
yami_music_player-1.0.1.dist-info/RECORD
