Metadata-Version: 2.1
Name: yami-music-player
Version: 1.0.1
Summary: An open-source music player with simple UI
Author-email: Mithun <mg.a54@proton.me>
Maintainer-email: Mithun <mg.a54@proton.me>
License:                     GNU GENERAL PUBLIC LICENSE
Project-URL: Documentation, https://github.com/dever-m/yami/blob/main/README.md
Project-URL: Bug Tracker, https://github.com/dever-m/yami/issues
Project-URL: Source code, https://github.com/dever-m/yami
Keywords: tkinter,youtube-music-player,spotdl,online-music-player,customtkinter,youtube-dl,music-player,spotify
Classifier: Development Status :: 5 - Production/Stable
Classifier: Intended Audience :: End Users/Desktop
Classifier: Operating System :: OS Independent
Classifier: License :: OSI Approved :: GNU General Public License (GPL)
Classifier: Programming Language :: Python :: 3
Requires-Python: >=3.8
License-File: LICENSE
Requires-Dist: customtkinter-fix-locale-scaling==5.2.2
Requires-Dist: mutagen==1.47.0
Requires-Dist: Pillow==11.0.0
Requires-Dist: pygame==2.6.1
Requires-Dist: spotdl==4.2.8
Requires-Dist: tk
